{
	"$schema": "https://raw.githubusercontent.com/DanielGavin/ols/master/misc/ols.schema.json",
	"collections": [
		{ "name": "custom_collection", "path": "c:/path/to/collection" }
	],
	"enable_semantic_tokens": false,
	"enable_document_symbols": true,
	"enable_hover": true,
	"enable_format": true,
	"enable_snippets": true,
	"enable_inlay_hints": true,
	"profile": "default",
	"profiles": [
		{ "name": "default", "checker_path": ["src"]},
		{ "name": "linux_profile", "os": "linux", "checker_path": ["src/main.odin"]},
		{ "name": "windows_profile", "os": "windows", "checker_path": ["src"]}
	]
}
